graphs.py
numbertheory.py
rangeQueries.py
datlib-0.0.3.dist-info/LICENSE.txt
datlib-0.0.3.dist-info/METADATA
datlib-0.0.3.dist-info/WHEEL
datlib-0.0.3.dist-info/top_level.txt
datlib-0.0.3.dist-info/RECORD
