Metadata-Version: 2.1
Name: datlib
Version: 0.0.3
Summary: A python package for data structures and algorithms.
Home-page: https://github.com/iamskp99/datlib.git
Author: Shashank Kumar Pandey
Author-email: iamskp99@gmail.com
License: UNKNOWN
Platform: UNKNOWN
Classifier: Development Status :: 5 - Production/Stable
Classifier: Intended Audience :: Education
Classifier: Operating System :: Microsoft :: Windows :: Windows 10
Classifier: License :: OSI Approved :: MIT License
Classifier: Programming Language :: Python :: 3
Classifier: Programming Language :: Python :: 3.6
Classifier: Programming Language :: Python :: 3.7
Classifier: Programming Language :: Python :: 3.9
